<?xml version="1.0" encoding="UTF-8"?>
<objects serializationModel="Studio.02.02.00">
	<object class="AudioFile" id="{255475cf-ea6e-4786-953b-c8b61aba3b85}">
		<property name="assetPath">
			<value>Corrent normal/Corrent normal 1.wav</value>
		</property>
		<property name="frequencyInKHz">
			<value>48</value>
		</property>
		<property name="channelCount">
			<value>2</value>
		</property>
		<property name="length">
			<value>1.4880208333333333</value>
		</property>
		<relationship name="masterAssetFolder">
			<destination>{296c0b8c-79cf-46be-bd1d-56635a36b440}</destination>
		</relationship>
	</object>
</objects>
